cnnfortsp/__init__.py
cnnftsp-2.0.1.dist-info/METADATA
cnnftsp-2.0.1.dist-info/WHEEL
cnnftsp-2.0.1.dist-info/top_level.txt
cnnftsp-2.0.1.dist-info/RECORD
