Metadata-Version: 2.1
Name: cnnftsp
Version: 2.0.1
Summary: CNN for TSP
Home-page: UNKNOWN
Author: Sikorski Philipp
Author-email: philipp.sikorski@uni-jena.de
License: MIT
Platform: UNKNOWN
